capcomposer/__init__.py
capcomposer/gunicorn.config.py
capcomposer/manage.py
capcomposer/version.py
capcomposer/cap/__init__.py
capcomposer/cap/admin.py
capcomposer/cap/apps.py
capcomposer/cap/cache.py
capcomposer/cap/exceptions.py
capcomposer/cap/mixins.py
capcomposer/cap/models.py
capcomposer/cap/permissions.py
capcomposer/cap/serializers.py
capcomposer/cap/sign.py
capcomposer/cap/static_map.py
capcomposer/cap/tasks.py
capcomposer/cap/tests.py
capcomposer/cap/urls.py
capcomposer/cap/utils.py
capcomposer/cap/views.py
capcomposer/cap/wagtail_hooks.py
capcomposer/cap/weasyprint_utils.py
capcomposer/cap/external_feed/__init__.py
capcomposer/cap/external_feed/models.py
capcomposer/cap/external_feed/utils.py
capcomposer/cap/locale/am/LC_MESSAGES/django.mo
capcomposer/cap/locale/am/LC_MESSAGES/django.po
capcomposer/cap/locale/ar/LC_MESSAGES/django.mo
capcomposer/cap/locale/ar/LC_MESSAGES/django.po
capcomposer/cap/locale/en/LC_MESSAGES/django.mo
capcomposer/cap/locale/en/LC_MESSAGES/django.po
capcomposer/cap/locale/es/LC_MESSAGES/django.mo
capcomposer/cap/locale/es/LC_MESSAGES/django.po
capcomposer/cap/locale/fr/LC_MESSAGES/django.mo
capcomposer/cap/locale/fr/LC_MESSAGES/django.po
capcomposer/cap/locale/sw/LC_MESSAGES/django.mo
capcomposer/cap/locale/sw/LC_MESSAGES/django.po
capcomposer/cap/management/__init__.py
capcomposer/cap/management/commands/__init__.py
capcomposer/cap/management/commands/create_cap_alerts_multi_media.py
capcomposer/cap/migrations/0001_initial.py
capcomposer/cap/migrations/0002_alter_capalertpage_info.py
capcomposer/cap/migrations/0003_capalertpage_search_image.py
capcomposer/cap/migrations/0004_alter_capalertpage_identifier.py
capcomposer/cap/migrations/0005_capalertlistpage.py
capcomposer/cap/migrations/0006_remove_capalertlistpage_description_and_more.py
capcomposer/cap/migrations/0007_alter_capalertpage_info.py
capcomposer/cap/migrations/0008_alter_capalertpage_info.py
capcomposer/cap/migrations/0009_merge_20231114_0803.py
cap_composer-1.2.0.dist-info/METADATA
cap_composer-1.2.0.dist-info/WHEEL
cap_composer-1.2.0.dist-info/entry_points.txt
cap_composer-1.2.0.dist-info/top_level.txt
cap_composer-1.2.0.dist-info/RECORD
