Metadata-Version: 2.4
Name: cap-composer
Version: 1.2.0
Summary: Wagtail based weather warnings composing and dissemination tool, using Common Alerting Protocol (CAP) standard.
Author-email: Erick Otenyo <otenyo.erick@gmail.com>, Grace Amondi <miswa.grace@gmail.com>
License: MIT
Project-URL: Homepage, https://github.com/wmo-raf/cap-composer
Project-URL: Bug Tracker, https://github.com/wmo-raf/cap-composer/issues
Platform: Linux
Classifier: Development Status :: 5 - Production/Stable
Classifier: Intended Audience :: Developers
Classifier: License :: OSI Approved :: MIT License
Classifier: Programming Language :: Python :: 3.8
Classifier: Programming Language :: Python :: 3.9
Classifier: Programming Language :: Python :: 3.10
Classifier: Framework :: Django
Classifier: Framework :: Wagtail
Requires-Python: >=3.8
Requires-Dist: wagtail>=7.0
Requires-Dist: djangorestframework-xml
Requires-Dist: python-magic
Requires-Dist: shapely
Requires-Dist: wagtail-icon-chooser>=0.3.1
Requires-Dist: wagtail-cache==3.0.0
Requires-Dist: adm-boundary-manager>=0.2.5
Requires-Dist: wagtail-humanitarian-icons>=2.0.0
Requires-Dist: wagtail-modelchooser>=4.0.1
Requires-Dist: paho-mqtt>=2.1.0
Requires-Dist: xmltodict>=0.14.2
Requires-Dist: pdf2image>=1.17.0
Requires-Dist: wagtail-metadata>=5.0.0
Requires-Dist: lxml>=5.4.0
Requires-Dist: signxml>=4.0.3
Requires-Dist: loguru>=0.7.3
Requires-Dist: weasyprint>=65.1
Requires-Dist: requests>=2.32.3
Requires-Dist: pytz>=2025.2
Requires-Dist: wagtail-lazyimages==0.1.5
Requires-Dist: wagtail-font-awesome-svg>=1.0.1
Requires-Dist: capvalidator==0.1.0.dev4
Requires-Dist: feedparser>=6.0.11
Requires-Dist: staticmap==0.5.7
Requires-Dist: wagtail-newsletter==0.2.2
Requires-Dist: mailchimp-marketing==3.0.80
Requires-Dist: mrml>=0.2
Requires-Dist: Pygments
Requires-Dist: markdown
